riskflow/__init__.py
riskflow/_version.py
riskflow/adaptiv.py
riskflow/bootstrappers.py
riskflow/calculation.py
riskflow/config.py
riskflow/documentation.py
riskflow/fields.py
riskflow/instruments.py
riskflow/pricing.py
riskflow/riskfactors.py
riskflow/stochasticprocess.py
riskflow/utils.py
riskflow-0.3.1.dev0.dist-info/LICENSE
riskflow-0.3.1.dev0.dist-info/METADATA
riskflow-0.3.1.dev0.dist-info/WHEEL
riskflow-0.3.1.dev0.dist-info/entry_points.txt
riskflow-0.3.1.dev0.dist-info/top_level.txt
riskflow-0.3.1.dev0.dist-info/RECORD
