Metadata-Version: 2.1
Name: riskflow
Version: 0.3.1.dev0
Summary: An XVA quantitative library with AAD
Home-page: https://github.com/sylam/riskflow
Author: shuaib.osman
Author-email: shuaib.osman@investec.co.za
License: GPLv3
Classifier: Development Status :: 4 - Beta
Classifier: Intended Audience :: Developers
Classifier: Intended Audience :: Science/Research
Classifier: Programming Language :: Python :: 3.6
Requires-Python: >=3.6
License-File: LICENSE
Requires-Dist: numpy (>=1.16.1)
Requires-Dist: scipy (>=1.2.2)
Requires-Dist: pandas (>=1.0)
Requires-Dist: matplotlib (>=3.0)
Requires-Dist: torch (>=1.11.0)
Requires-Dist: python-markdown-math (>=0.6)
Provides-Extra: interactive
Requires-Dist: jupyter ; extra == 'interactive'
